ppl/__init__.py
ppl/3rd/bin/ppl-compile
ppl/3rd/bin/ppl_jit.sh
ppl/3rd/deps/CMakeLists.txt
ppl/3rd/deps/chip/chip_map.json
ppl/3rd/deps/chip/tpu_6_0/config_common.cmake
ppl/3rd/deps/chip/tpu_6_0/memmap.h
ppl/3rd/deps/chip/tpu_6_0/TPU1686/kernel/include/memmap.h
ppl/3rd/deps/chip/tpu_6_0/TPU1686/kernel/include/tpu_defs.h
ppl/3rd/deps/chip/tpu_6_0/TPU1686/kernel/include/tpu_kernel.h
ppl/3rd/deps/chip/tpu_6_0/TPU1686/tpuDNN/include/tpuDNN.h
ppl/3rd/deps/chip/tpu_6_0/TPU1686/tpuDNN/include/tpuDNNLegacy.h
ppl/3rd/deps/chip/tpu_6_0/TPU1686/tpuDNN/include/tpuDNNTensor.h
ppl/3rd/deps/chip/tpu_6_0_e/config_common.cmake
ppl/3rd/deps/chip/tpu_6_0_e/memmap.h
ppl/3rd/deps/chip/tpu_6_0_e/TPU1686/kernel/include/memmap.h
ppl/3rd/deps/chip/tpu_6_0_e/TPU1686/kernel/include/tpu_defs.h
ppl/3rd/deps/chip/tpu_6_0_e/TPU1686/kernel/include/tpu_kernel.h
ppl/3rd/deps/chip/tpu_6_0_e/TPU1686/tpuDNN/include/tpuDNN.h
ppl/3rd/deps/chip/tpu_6_0_e/TPU1686/tpuDNN/include/tpuDNNLegacy.h
ppl/3rd/deps/chip/tpu_6_0_e/TPU1686/tpuDNN/include/tpuDNNTensor.h
ppl/3rd/deps/chip/tpub_7_1/config_common.cmake
ppl/3rd/deps/chip/tpub_7_1/memmap.h
ppl/3rd/deps/chip/tpub_7_1/TPU1686/kernel/include/memmap.h
ppl/3rd/deps/chip/tpub_7_1/TPU1686/kernel/include/tpu_defs.h
ppl/3rd/deps/chip/tpub_7_1/TPU1686/kernel/include/tpu_kernel.h
ppl/3rd/deps/chip/tpub_7_1/TPU1686/kernel/include/tpu_macros.h
ppl/3rd/deps/chip/tpub_7_1/TPU1686/kernel/include/tpu_utils.h
ppl/3rd/deps/chip/tpub_7_1/TPU1686/tpuDNN/include/tpuDNN.h
ppl/3rd/deps/chip/tpub_7_1/TPU1686/tpuDNN/include/tpuDNNLegacy.h
ppl/3rd/deps/chip/tpub_7_1/TPU1686/tpuDNN/include/tpuDNNTensor.h
ppl/3rd/deps/chip/tpub_7_1_e/atomic_def.h
ppl/3rd/deps/chip/tpub_7_1_e/config_common.cmake
ppl/3rd/deps/chip/tpub_7_1_e/TPU1686/kernel/include/atomic_def.h
ppl/3rd/deps/chip/tpub_7_1_e/TPU1686/kernel/include/rvt_api.h
ppl/3rd/deps/chip/tpub_7_1_e/TPU1686/kernel/include/tpu_defs.h
ppl/3rd/deps/chip/tpub_7_1_e/TPU1686/kernel/include/tpu_kernel.h
tpu_ppl-1.6.19.dist-info/METADATA
tpu_ppl-1.6.19.dist-info/WHEEL
tpu_ppl-1.6.19.dist-info/top_level.txt
tpu_ppl-1.6.19.dist-info/RECORD
