Metadata-Version: 2.4
Name: tpu_ppl
Version: 1.6.19
Summary: A language and compiler for custom Deep Learning operations
Home-page: https://github.com/sophgo/PPL/
Author: liang.chen
Author-email: liang.chen@sophgo.com
License: 2-Clause BSD
Keywords: Compiler,Deep Learning
Classifier: Development Status :: 4 - Beta
Classifier: Intended Audience :: Developers
Classifier: Topic :: Software Development :: Build Tools
Classifier: License :: OSI Approved :: MIT License
Classifier: Programming Language :: Python :: 3.8
Classifier: Programming Language :: Python :: 3.9
Classifier: Programming Language :: Python :: 3.10
Classifier: Programming Language :: Python :: 3.11
Classifier: Programming Language :: Python :: 3.12
Requires-Python: >=3.8
Provides-Extra: build
Requires-Dist: cmake>=3.20; extra == "build"
Requires-Dist: lit; extra == "build"
Dynamic: author
Dynamic: author-email
Dynamic: classifier
Dynamic: description
Dynamic: description-content-type
Dynamic: home-page
Dynamic: keywords
Dynamic: license
Dynamic: provides-extra
Dynamic: requires-python
Dynamic: summary
